nexula/__init__.py
nexula/api_client.py
nexula/cli.py
nexula/config.py
nexula/commands/__init__.py
nexula/commands/aibom.py
nexula/commands/auth.py
nexula/commands/init.py
nexula/commands/scan.py
nexula_cli-2.0.1.dist-info/METADATA
nexula_cli-2.0.1.dist-info/WHEEL
nexula_cli-2.0.1.dist-info/entry_points.txt
nexula_cli-2.0.1.dist-info/top_level.txt
nexula_cli-2.0.1.dist-info/RECORD
