Metadata-Version: 2.4
Name: nexula-cli
Version: 2.0.1
Summary: Enterprise CLI for AI/ML Security with Interactive Remediation - Scan, Fix, and Secure AI Supply Chains
Home-page: https://github.com/Nexula-AI/nexula-cli
Author: Nexula AI
Project-URL: Documentation, https://docs.nexula.one
Project-URL: Source, https://github.com/Nexula-AI/nexula-cli
Project-URL: Tracker, https://github.com/Nexula-AI/nexula-cli/issues
Keywords: security ai ml vulnerability scanner sast devsecops
Classifier: Development Status :: 5 - Production/Stable
Classifier: Intended Audience :: Developers
Classifier: Topic :: Security
Classifier: Topic :: Software Development :: Quality Assurance
Classifier: License :: OSI Approved :: MIT License
Classifier: Programming Language :: Python :: 3
Classifier: Programming Language :: Python :: 3.8
Classifier: Programming Language :: Python :: 3.9
Classifier: Programming Language :: Python :: 3.10
Classifier: Programming Language :: Python :: 3.11
Requires-Python: >=3.8
Requires-Dist: click>=8.1.0
Requires-Dist: requests>=2.31.0
Requires-Dist: pyyaml>=6.0
Requires-Dist: rich>=13.0.0
Requires-Dist: tabulate>=0.9.0
Dynamic: author
Dynamic: classifier
Dynamic: description
Dynamic: description-content-type
Dynamic: home-page
Dynamic: keywords
Dynamic: project-url
Dynamic: requires-dist
Dynamic: requires-python
Dynamic: summary
